Metadata-Version: 2.1
Name: pyfongo
Version: 0.1.0
Summary: Serverless self-contained database with pymongo interface
Home-page: https://github.com/krisfris/pyfongo
Author: Kris
Author-email: 31852063+krisfris@users.noreply.github.com
License: MIT
Download-URL: https://github.com/krisfris/pytest-krisfris/tarball/0.1.0
Platform: UNKNOWN
